{
  "openapi": "3.0.2",
  "paths": {
    "/runs/A": {
      "post": {
        "tags": [],
        "parameters": [],
        "requestBody": {
          "description": "Body",
          "content": {
            "application/json": {
              "schema": {
                "type": "object",
                "properties": {
                  "repo_id": {
                    "type": "string"
                  }
                },
                "required": [
                  "repo_id"
                ]
              }
            }
          }
        },
        "responses": {
          "202": {
            "description": "202",
            "content": {
              "application/json": {
                "schema": {
                  "type": "object",
                  "properties": {
                    "run_id": {
                      "type": "string"
                    }
                  },
                  "required": [
                    "run_id"
                  ]
                }
              }
            }
          }
        }
      }
    },
    "/runs/D": {
      "post": {
        "tags": [],
        "parameters": [],
        "requestBody": {
          "description": "Body",
          "content": {
            "application/json": {
              "schema": {
                "type": "object",
                "properties": {
                  "repo_id": {
                    "type": "string"
                  },
                  "tag": {
                    "type": "string"
                  }
                },
                "required": [
                  "repo_id"
                ]
              }
            }
          }
        },
        "responses": {
          "202": {
            "description": "202",
            "content": {
              "application/json": {
                "schema": {
                  "type": "object",
                  "properties": {
                    "run_id": {
                      "type": "string"
                    }
                  },
                  "required": [
                    "run_id"
                  ]
                }
              }
            }
          }
        }
      }
    }
  },
  "info": {
    "title": "Runs API",
    "version": "1.0.0"
  }
}